setup.py
frasco_sharejs/__init__.py
frasco_sharejs/api.py
frasco_sharejs.egg-info/PKG-INFO
frasco_sharejs.egg-info/SOURCES.txt
frasco_sharejs.egg-info/dependency_links.txt
frasco_sharejs.egg-info/not-zip-safe
frasco_sharejs.egg-info/requires.txt
frasco_sharejs.egg-info/top_level.txt
frasco_sharejs/sharejs/package.json
frasco_sharejs/sharejs/server.js
frasco_sharejs/static/bcsocket.js
frasco_sharejs/static/connect.js
frasco_sharejs/static/json0.js
frasco_sharejs/static/reconnecting-websocket.js
frasco_sharejs/static/share.js
frasco_sharejs/static/text.js