Metadata-Version: 1.0
Name: frasco-sharejs
Version: 0.1.1
Summary: Sharejs integration into Frasco
Home-page: http://github.com/frascoweb/frasco-sharejs
Author: Maxime Bouroumeau-Fuseau
Author-email: maxime.bouroumeau@gmail.com
License: MIT
Platform: any
